dev/Integration_TB/master/Master_slot.v
module Master_slot (
    input wire resetn,
    input wire clk,
    input wire [9:0] DIV,
    input wire [9:0] GUARD_TICKS,
    input wire [2:0] NODE_CNT,

    output reg  [2:0] slot,
    output reg        slot_change,
    output reg        slot_pre_change,
    output reg  [15:0] clk_cnt,
    output wire [1:0] rx_stat,
    output reg  [63:0] cycle_cnt
);

  wire [15:0] data_len_tick = 16'd50 * DIV;
  wire [15:0] total_tick = data_len_tick + {6'b0, GUARD_TICKS};

  // 슬롯 0..NODE_CNT: 슬레이브 슬롯, NODE_CNT+1: 마스터 DATA 슬롯
  wire [2:0] last_slot = NODE_CNT + 3'd1;

  always @(posedge clk or negedge resetn) begin
      if (!resetn) begin
          clk_cnt <= 16'd0;
          slot <= 3'd0;
          slot_change <= 1'b1;
          cycle_cnt <= 64'b0;
      end
      else begin
          if((clk_cnt == (total_tick - 16'd1))) begin
            clk_cnt <= 16'd0;
            if(slot == last_slot) begin
              slot <= 3'd0;
              cycle_cnt <= cycle_cnt + 64'b1;
            end
            else
              slot <= slot + 3'd1;
            slot_change <= 1'b1;
          end
          else begin
            clk_cnt <= clk_cnt + 16'd1;
            slot <= slot;
            slot_change <= 1'b0;
          end
      end
  end

  always @(posedge clk or negedge resetn) begin
      if (!resetn) begin
          slot_pre_change <= 1'b0;
      end
      else begin
          if(clk_cnt == (total_tick - 16'd2)) begin
            slot_pre_change <= 1'b1;
          end
          else begin
            slot_pre_change <= 1'b0;
          end
      end
  end

  assign rx_stat = (clk_cnt < data_len_tick) ? 2'd2 :
                   ((data_len_tick + (GUARD_TICKS>>2) <= clk_cnt) && (clk_cnt < total_tick - (GUARD_TICKS>>2))) ? 2'd0 : 2'd1;

endmodule

dev/Integration_TB/master/tb_master_slot.v
`timescale 1ns/1ps
// tb_master_slot: Master_slot 단위 테스트
// 컴파일: vlog Master_slot.v tb_master_slot.v
// 실행: vsim -c tb_master_slot -do "run -all; quit"
//
// 파라미터: DIV=4, GUARD=20, NODE_CNT=2
//   slot_ticks = 50*4+20 = 220
//   last_slot  = NODE_CNT+1 = 3
//   전체 주기  = 4 슬롯 × 220 = 880 클럭
module tb_master_slot;

localparam CLK_HALF  = 5;
localparam [9:0] DIV   = 10'd4;
localparam [9:0] GUARD = 10'd20;
localparam [2:0] NCNT  = 3'd2;          // NODE_CNT
localparam       SLOT_TICKS = 50*4+20;  // 220
localparam       LAST_SLOT  = NCNT+1;   // 3

reg clk = 0, resetn = 0;
always #CLK_HALF clk = ~clk;

wire [2:0]  slot;
wire        slot_change, slot_pre_change;
wire [15:0] clk_cnt;
wire [1:0]  rx_stat;
wire [63:0] cycle_cnt;

Master_slot dut (
    .resetn(resetn), .clk(clk),
    .DIV(DIV), .GUARD_TICKS(GUARD), .NODE_CNT(NCNT),
    .slot(slot), .slot_change(slot_change), .slot_pre_change(slot_pre_change),
    .clk_cnt(clk_cnt), .rx_stat(rx_stat), .cycle_cnt(cycle_cnt)
);

integer fail = 0, pass = 0;

task chk;
    input cond;
    input [127:0] msg;
    begin
        if (cond) begin $display("  PASS | %0s", msg); pass = pass + 1; end
        else      begin $display("  FAIL | %0s", msg); fail = fail + 1; end
    end
endtask

// 슬롯 시퀀스 기록
reg [2:0] slot_seq [0:7];
integer   seq_idx;
reg       change_latch;

integer i;

initial begin
    $dumpfile("tb_master_slot.vcd");
    $dumpvars(0, tb_master_slot);

    resetn = 0;
    repeat(4) @(posedge clk);
    resetn = 1;
    @(posedge clk); // slot_change=1 at reset release

    // --- SC1: 슬롯 시퀀스 확인 (2 전체 주기) ---
    $display("[%0t] SC1: 슬롯 시퀀스 검증", $time);
    seq_idx = 0;
    // slot_change=1 인 클럭을 포착하며 슬롯 번호 기록
    begin : seq_check
        integer cyc;
        for (cyc = 0; cyc < 2*4*SLOT_TICKS; cyc = cyc + 1) begin
            @(posedge clk);
            if (slot_change && seq_idx < 8)
                slot_seq[seq_idx] = slot;
            if (slot_change)
                seq_idx = seq_idx + 1;
        end
    end
    // 예상 시퀀스: 1,2,3,0,1,2,3,0 (slot_change 시점의 slot 값)
    chk(slot_seq[0]==3'd1, "seq[0]==1");
    chk(slot_seq[1]==3'd2, "seq[1]==2");
    chk(slot_seq[2]==3'd3, "seq[2]==3 (master_slot)");
    chk(slot_seq[3]==3'd0, "seq[3]==0 (wrap)");
    chk(slot_seq[4]==3'd1, "seq[4]==1 (2nd cycle)");
    chk(slot_seq[7]==3'd0, "seq[7]==0 (2nd wrap)");

    // --- SC2: cycle_cnt ---
    $display("[%0t] SC2: cycle_cnt 검증", $time);
    // 리셋 후 2 전체 주기 경과 = cycle_cnt >= 2
    chk(cycle_cnt >= 64'd2, "cycle_cnt >= 2 after 2 full cycles");

    // --- SC3: slot_pre_change 타이밍 ---
    // slot_pre_change는 slot_change 1클럭 전에 와야 함
    $display("[%0t] SC3: slot_pre_change 1클럭 전 검증", $time);
    begin : pre_chk
        integer w;
        reg pre_seen;
        pre_seen = 0;
        for (w = 0; w < SLOT_TICKS+10; w = w + 1) begin
            @(posedge clk);
            if (slot_pre_change) pre_seen = 1;
            if (slot_change) begin
                chk(pre_seen, "slot_pre_change came before slot_change");
                pre_seen = 0;
            end
        end
    end

    // --- SC4: rx_stat 윈도우 ---
    // clk_cnt < data_len_tick(200) → 2, 중간 guard 구간 → 0, edge → 1
    $display("[%0t] SC4: rx_stat 검증", $time);
    // clk_cnt=0: rx_stat=2
    // clk_cnt=205 (200+5=data+guard/4): rx_stat=0 window 시작
    // wait until next slot_change
    begin : wait_sc
        forever begin
            @(posedge clk);
            if (slot_change) disable wait_sc;
        end
    end
    @(posedge clk);
    chk(rx_stat==2'd2, "rx_stat=2 at clk_cnt=0");
    // wait for data period end
    repeat(200) @(posedge clk);
    // clk_cnt=200: guard 시작, rx_stat=1 (guard/4=5 아직 안됨)
    chk(rx_stat==2'd1, "rx_stat=1 at guard start");
    repeat(5) @(posedge clk);
    // clk_cnt=205: rx_stat=0 detection window
    chk(rx_stat==2'd0, "rx_stat=0 in detection window");

    $display("");
    $display("=== Result: %0d PASS  %0d FAIL ===", pass, fail);
    $finish;
end

initial begin
    #500_000;
    $display("TIMEOUT");
    $finish;
end

endmodule

dev/Integration_TB/tb_master_slot.vcd
$date
	Tue Jun 02 18:18:23 2026
$end
$version
	ModelSim Version 10.5b
$end
$timescale
	1ps
$end

$scope module tb_master_slot $end
$var parameter 32 ! CLK_HALF $end
$var parameter 10 " DIV $end
$var parameter 10 # GUARD $end
$var parameter 3 $ NCNT $end
$var parameter 32 % SLOT_TICKS $end
$var parameter 32 & LAST_SLOT $end
$var reg 1 ' clk $end
$var reg 1 ( resetn $end
$var wire 1 ) slot [2] $end
$var wire 1 * slot [1] $end
$var wire 1 + slot [0] $end
$var wire 1 , slot_change $end
$var wire 1 - slot_pre_change $end
$var wire 1 . clk_cnt [15] $end
$var wire 1 / clk_cnt [14] $end
$var wire 1 0 clk_cnt [13] $end
$var wire 1 1 clk_cnt [12] $end
$var wire 1 2 clk_cnt [11] $end
$var wire 1 3 clk_cnt [10] $end
$var wire 1 4 clk_cnt [9] $end
$var wire 1 5 clk_cnt [8] $end
$var wire 1 6 clk_cnt [7] $end
$var wire 1 7 clk_cnt [6] $end
$var wire 1 8 clk_cnt [5] $end
$var wire 1 9 clk_cnt [4] $end
$var wire 1 : clk_cnt [3] $end
$var wire 1 ; clk_cnt [2] $end
$var wire 1 < clk_cnt [1] $end
$var wire 1 = clk_cnt [0] $end
$var wire 1 > rx_stat [1] $end
$var wire 1 ? rx_stat [0] $end
$var wire 1 @ cycle_cnt [63] $end
$var wire 1 A cycle_cnt [62] $end
$var wire 1 B cycle_cnt [61] $end
$var wire 1 C cycle_cnt [60] $end
$var wire 1 D cycle_cnt [59] $end
$var wire 1 E cycle_cnt [58] $end
$var wire 1 F cycle_cnt [57] $end
$var wire 1 G cycle_cnt [56] $end
$var wire 1 H cycle_cnt [55] $end
$var wire 1 I cycle_cnt [54] $end
$var wire 1 J cycle_cnt [53] $end
$var wire 1 K cycle_cnt [52] $end
$var wire 1 L cycle_cnt [51] $end
$var wire 1 M cycle_cnt [50] $end
$var wire 1 N cycle_cnt [49] $end
$var wire 1 O cycle_cnt [48] $end
$var wire 1 P cycle_cnt [47] $end
$var wire 1 Q cycle_cnt [46] $end
$var wire 1 R cycle_cnt [45] $end
$var wire 1 S cycle_cnt [44] $end
$var wire 1 T cycle_cnt [43] $end
$var wire 1 U cycle_cnt [42] $end
$var wire 1 V cycle_cnt [41] $end
$var wire 1 W cycle_cnt [40] $end
$var wire 1 X cycle_cnt [39] $end
$var wire 1 Y cycle_cnt [38] $end
$var wire 1 Z cycle_cnt [37] $end
$var wire 1 [ cycle_cnt [36] $end
$var wire 1 \ cycle_cnt [35] $end
$var wire 1 ] cycle_cnt [34] $end
$var wire 1 ^ cycle_cnt [33] $end
$var wire 1 _ cycle_cnt [32] $end
$var wire 1 ` cycle_cnt [31] $end
$var wire 1 a cycle_cnt [30] $end
$var wire 1 b cycle_cnt [29] $end
$var wire 1 c cycle_cnt [28] $end
$var wire 1 d cycle_cnt [27] $end
$var wire 1 e cycle_cnt [26] $end
$var wire 1 f cycle_cnt [25] $end
$var wire 1 g cycle_cnt [24] $end
$var wire 1 h cycle_cnt [23] $end
$var wire 1 i cycle_cnt [22] $end
$var wire 1 j cycle_cnt [21] $end
$var wire 1 k cycle_cnt [20] $end
$var wire 1 l cycle_cnt [19] $end
$var wire 1 m cycle_cnt [18] $end
$var wire 1 n cycle_cnt [17] $end
$var wire 1 o cycle_cnt [16] $end
$var wire 1 p cycle_cnt [15] $end
$var wire 1 q cycle_cnt [14] $end
$var wire 1 r cycle_cnt [13] $end
$var wire 1 s cycle_cnt [12] $end
$var wire 1 t cycle_cnt [11] $end
$var wire 1 u cycle_cnt [10] $end
$var wire 1 v cycle_cnt [9] $end
$var wire 1 w cycle_cnt [8] $end
$var wire 1 x cycle_cnt [7] $end
$var wire 1 y cycle_cnt [6] $end
$var wire 1 z cycle_cnt [5] $end
$var wire 1 { cycle_cnt [4] $end
$var wire 1 | cycle_cnt [3] $end
$var wire 1 } cycle_cnt [2] $end
$var wire 1 ~ cycle_cnt [1] $end
$var wire 1 !! cycle_cnt [0] $end
$var integer 32 "! fail $end
$var integer 32 #! pass $end
$var integer 32 $! seq_idx $end
$var reg 1 %! change_latch $end
$var integer 32 &! i $end

$scope task chk $end
$var reg 1 '! cond $end
$var reg 128 (! msg [127:0] $end
$upscope $end

$scope begin seq_check $end
$var integer 32 )! cyc $end
$upscope $end

$scope begin pre_chk $end
$var integer 32 *! w $end
$var reg 1 +! pre_seen $end
$upscope $end

$scope begin wait_sc $end
$upscope $end

$scope module dut $end
$var wire 1 ,! resetn $end
$var wire 1 -! clk $end
$var wire 1 .! DIV [9] $end
$var wire 1 /! DIV [8] $end
$var wire 1 0! DIV [7] $end
$var wire 1 1! DIV [6] $end
$var wire 1 2! DIV [5] $end
$var wire 1 3! DIV [4] $end
$var wire 1 4! DIV [3] $end
$var wire 1 5! DIV [2] $end
$var wire 1 6! DIV [1] $end
$var wire 1 7! DIV [0] $end
$var wire 1 8! GUARD_TICKS [9] $end
$var wire 1 9! GUARD_TICKS [8] $end
$var wire 1 :! GUARD_TICKS [7] $end
$var wire 1 ;! GUARD_TICKS [6] $end
$var wire 1 <! GUARD_TICKS [5] $end
$var wire 1 =! GUARD_TICKS [4] $end
$var wire 1 >! GUARD_TICKS [3] $end
$var wire 1 ?! GUARD_TICKS [2] $end
$var wire 1 @! GUARD_TICKS [1] $end
$var wire 1 A! GUARD_TICKS [0] $end
$var wire 1 B! NODE_CNT [2] $end
$var wire 1 C! NODE_CNT [1] $end
$var wire 1 D! NODE_CNT [0] $end
$var reg 3 E! slot [2:0] $end
$var reg 1 F! slot_change $end
$var reg 1 G! slot_pre_change $end
$var reg 16 H! clk_cnt [15:0] $end
$var wire 1 > rx_stat [1] $end
$var wire 1 ? rx_stat [0] $end
$var reg 64 I! cycle_cnt [63:0] $end
$var wire 1 J! data_len_tick [15] $end
$var wire 1 K! data_len_tick [14] $end
$var wire 1 L! data_len_tick [13] $end
$var wire 1 M! data_len_tick [12] $end
$var wire 1 N! data_len_tick [11] $end
$var wire 1 O! data_len_tick [10] $end
$var wire 1 P! data_len_tick [9] $end
$var wire 1 Q! data_len_tick [8] $end
$var wire 1 R! data_len_tick [7] $end
$var wire 1 S! data_len_tick [6] $end
$var wire 1 T! data_len_tick [5] $end
$var wire 1 U! data_len_tick [4] $end
$var wire 1 V! data_len_tick [3] $end
$var wire 1 W! data_len_tick [2] $end
$var wire 1 X! data_len_tick [1] $end
$var wire 1 Y! data_len_tick [0] $end
$var wire 1 Z! total_tick [15] $end
$var wire 1 [! total_tick [14] $end
$var wire 1 \! total_tick [13] $end
$var wire 1 ]! total_tick [12] $end
$var wire 1 ^! total_tick [11] $end
$var wire 1 _! total_tick [10] $end
$var wire 1 `! total_tick [9] $end
$var wire 1 a! total_tick [8] $end
$var wire 1 b! total_tick [7] $end
$var wire 1 c! total_tick [6] $end
$var wire 1 d! total_tick [5] $end
$var wire 1 e! total_tick [4] $end
$var wire 1 f! total_tick [3] $end
$var wire 1 g! total_tick [2] $end
$var wire 1 h! total_tick [1] $end
$var wire 1 i! total_tick [0] $end
$var wire 1 j! last_slot [2] $end
$var wire 1 k! last_slot [1] $end
$var wire 1 l! last_slot [0] $end
$upscope $end
$upscope $end
$enddefinitions $end
#0
$dumpvars
0'
0(
b0 E!
1F!
0G!
b0 H!
b0 I!
x'!
bx (!
x%!
x+!
b101 !
b100 "
b10100 #
b10 $
b11011100 %
b11 &
b0 "!
b0 #!
bx $!
bx &!
bx )!
bx *!
0+
0*
0)
1,
0-
0=
0<
0;
0:
09
08
07
06
05
04
03
02
01
00
0/
0.
0?
1>
0!!
0~
0}
0|
0{
0z
0y
0x
0w
0v
0u
0t
0s
0r
0q
0p
0o
0n
0m
0l
0k
0j
0i
0h
0g
0f
0e
0d
0c
0b
0a
0`
0_
0^
0]
0\
0[
0Z
0Y
0X
0W
0V
0U
0T
0S
0R
0Q
0P
0O
0N
0M
0L
0K
0J
0I
0H
0G
0F
0E
0D
0C
0B
0A
0@
0Y!
0X!
0W!
1V!
0U!
0T!
1S!
1R!
0Q!
0P!
0O!
0N!
0M!
0L!
0K!
0J!
0i!
0h!
1g!
1f!
1e!
0d!
1c!
1b!
0a!
0`!
0_!
0^!
0]!
0\!
0[!
0Z!
1l!
1k!
0j!
0D!
1C!
0B!
0A!
0@!
1?!
0>!
1=!
0<!
0;!
0:!
09!
08!
07!
06!
15!
04!
03!
02!
01!
00!
0/!
0.!
0-!
0,!
$end
#5000
1'
1-!
#10000
0'
0-!
#15000
1'
1-!
#20000
0'
0-!
#25000
1'
1-!
#30000
0'
0-!
#35000
1'
1-!
1(
1,!
#40000
0'
0-!
#45000
1'
1-!
b0 $!
b0 )!
b1 H!
0F!
1=
0,
#50000
0'
0-!
#55000
1'
1-!
b1 )!
b10 H!
0=
1<
#60000
0'
0-!
#65000
1'
1-!
b10 )!
b11 H!
1=
#70000
0'
0-!
#75000
1'
1-!
b11 )!
b100 H!
0=
0<
1;
#80000
0'
0-!
#85000
1'
1-!
b100 )!
b101 H!
1=
#90000
0'
0-!
#95000
1'
1-!
b101 )!
b110 H!
0=
1<
#100000
0'
0-!
#105000
1'
1-!
b110 )!
b111 H!
1=
#110000
0'
0-!
#115000
1'
1-!
b111 )!
b1000 H!
0=
0<
0;
1:
#120000
0'
0-!
#125000
1'
1-!
b1000 )!
b1001 H!
1=
#130000
0'
0-!
#135000
1'
1-!
b1001 )!
b1010 H!
0=
1<
#140000
0'
0-!
#145000
1'
1-!
b1010 )!
b1011 H!
1=
#150000
0'
0-!
#155000
1'
1-!
b1011 )!
b1100 H!
0=
0<
1;
#160000
0'
0-!
#165000
1'
1-!
b1100 )!
b1101 H!
1=
#170000
0'
0-!
#175000
1'
1-!
b1101 )!
b1110 H!
0=
1<
#180000
0'
0-!
#185000
1'
1-!
b1110 )!
b1111 H!
1=
#190000
0'
0-!
#195000
1'
1-!
b1111 )!
b10000 H!
0=
0<
0;
0:
19
#200000
0'
0-!
#205000
1'
1-!
b10000 )!
b10001 H!
1=
#210000
0'
0-!
#215000
1'
1-!
b10001 )!
b10010 H!
0=
1<
#220000
0'
0-!
#225000
1'
1-!
b10010 )!
b10011 H!
1=
#230000
0'
0-!
#235000
1'
1-!
b10011 )!
b10100 H!
0=
0<
1;
#240000
0'
0-!
#245000
1'
1-!
b10100 )!
b10101 H!
1=
#250000
0'
0-!
#255000
1'
1-!
b10101 )!
b10110 H!
0=
1<
#260000
0'
0-!
#265000
1'
1-!
b10110 )!
b10111 H!
1=
#270000
0'
0-!
#275000
1'
1-!
b10111 )!
b11000 H!
0=
0<
0;
1:
#280000
0'
0-!
#285000
1'
1-!
b11000 )!
b11001 H!
1=
#290000
0'
0-!
#295000
1'
1-!
b11001 )!
b11010 H!
0=
1<
#300000
0'
0-!
#305000
1'
1-!
b11010 )!
b11011 H!
1=
#310000
0'
0-!
#315000
1'
1-!
b11011 )!
b11100 H!
0=
0<
1;
#320000
0'
0-!
#325000
1'
1-!
b11100 )!
b11101 H!
1=
#330000
0'
0-!
#335000
1'
1-!
b11101 )!
b11110 H!
0=
1<
#340000
0'
0-!
#345000
1'
1-!
b11110 )!
b11111 H!
1=
#350000
0'
0-!
#355000
1'
1-!
b11111 )!
b100000 H!
0=
0<
0;
0:
09
18
#360000
0'
0-!
#365000
1'
1-!
b100000 )!
b100001 H!
1=
#370000
0'
0-!
#375000
1'
1-!
b100001 )!
b100010 H!
0=
1<
#380000
0'
0-!
#385000
1'
1-!
b100010 )!
b100011 H!
1=
#390000
0'
0-!
#395000
1'
1-!
b100011 )!
b100100 H!
0=
0<
1;
#400000
0'
0-!
#405000
1'
1-!
b100100 )!
b100101 H!
1=
#410000
0'
0-!
#415000
1'
1-!
b100101 )!
b100110 H!
0=
1<
#420000
0'
0-!
#425000
1'
1-!
b100110 )!
b100111 H!
1=
#430000
0'
0-!
#435000
1'
1-!
b100111 )!
b101000 H!
0=
0<
0;
1:
#440000
0'
0-!
#445000
1'
1-!
b101000 )!
b101001 H!
1=
#450000
0'
0-!
#455000
1'
1-!
b101001 )!
b101010 H!
0=
1<
#460000
0'
0-!
#465000
1'
1-!
b101010 )!
b101011 H!
1=
#470000
0'
0-!
#475000
1'
1-!
b101011 )!
b101100 H!
0=
0<
1;
#480000
0'
0-!
#485000
1'
1-!
b101100 )!
b101101 H!
1=
#490000
0'
0-!
#495000
1'
1-!
b101101 )!
b101110 H!
0=
1<
#500000
0'
0-!
#505000
1'
1-!
b101110 )!
b101111 H!
1=
#510000
0'
0-!
#515000
1'
1-!
b101111 )!
b110000 H!
0=
0<
0;
0:
19
#520000
0'
0-!
#525000
1'
1-!
b110000 )!
b110001 H!
1=
#530000
0'
0-!
#535000
1'
1-!
b110001 )!
b110010 H!
0=
1<
#540000
0'
0-!
#545000
1'
1-!
b110010 )!
b110011 H!
1=
#550000
0'
0-!
#555000
1'
1-!
b110011 )!
b110100 H!
0=
0<
1;
#560000
0'
0-!
#565000
1'
1-!
b110100 )!
b110101 H!
1=
#570000
0'
0-!
#575000
1'
1-!
b110101 )!
b110110 H!
0=
1<
#580000
0'
0-!
#585000
1'
1-!
b110110 )!
b110111 H!
1=
#590000
0'
0-!
#595000
1'
1-!
b110111 )!
b111000 H!
0=
0<
0;
1:
#600000
0'
0-!
#605000
1'
1-!
b111000 )!
b111001 H!
1=
#610000
0'
0-!
#615000
1'
1-!
b111001 )!
b111010 H!
0=
1<
#620000
0'
0-!
#625000
1'
1-!
b111010 )!
b111011 H!
1=
#630000
0'
0-!
#635000
1'
1-!
b111011 )!
b111100 H!
0=
0<
1;
#640000
0'
0-!
#645000
1'
1-!
b111100 )!
b111101 H!
1=
#650000
0'
0-!
#655000
1'
1-!
b111101 )!
b111110 H!
0=
1<
#660000
0'
0-!
#665000
1'
1-!
b111110 )!
b111111 H!
1=
#670000
0'
0-!
#675000
1'
1-!
b111111 )!
b1000000 H!
0=
0<
0;
0:
09
08
17
#680000
0'
0-!
#685000
1'
1-!
b1000000 )!
b1000001 H!
1=
#690000
0'
0-!
#695000
1'
1-!
b1000001 )!
b1000010 H!
0=
1<
#700000
0'
0-!
#705000
1'
1-!
b1000010 )!
b1000011 H!
1=
#710000
0'
0-!
#715000
1'
1-!
b1000011 )!
b1000100 H!
0=
0<
1;
#720000
0'
0-!
#725000
1'
1-!
b1000100 )!
b1000101 H!
1=
#730000
0'
0-!
#735000
1'
1-!
b1000101 )!
b1000110 H!
0=
1<
#740000
0'
0-!
#745000
1'
1-!
b1000110 )!
b1000111 H!
1=
#750000
0'
0-!
#755000
1'
1-!
b1000111 )!
b1001000 H!
0=
0<
0;
1:
#760000
0'
0-!
#765000
1'
1-!
b1001000 )!
b1001001 H!
1=
#770000
0'
0-!
#775000
1'
1-!
b1001001 )!
b1001010 H!
0=
1<
#780000
0'
0-!
#785000
1'
1-!
b1001010 )!
b1001011 H!
1=
#790000
0'
0-!
#795000
1'
1-!
b1001011 )!
b1001100 H!
0=
0<
1;
#800000
0'
0-!
#805000
1'
1-!
b1001100 )!
b1001101 H!
1=
#810000
0'
0-!
#815000
1'
1-!
b1001101 )!
b1001110 H!
0=
1<
#820000
0'
0-!
#825000
1'
1-!
b1001110 )!
b1001111 H!
1=
#830000
0'
0-!
#835000
1'
1-!
b1001111 )!
b1010000 H!
0=
0<
0;
0:
19
#840000
0'
0-!
#845000
1'
1-!
b1010000 )!
b1010001 H!
1=
#850000
0'
0-!
#855000
1'
1-!
b1010001 )!
b1010010 H!
0=
1<
#860000
0'
0-!
#865000
1'
1-!
b1010010 )!
b1010011 H!
1=
#870000
0'
0-!
#875000
1'
1-!
b1010011 )!
b1010100 H!
0=
0<
1;
#880000
0'
0-!
#885000
1'
1-!
b1010100 )!
b1010101 H!
1=
#890000
0'
0-!
#895000
1'
1-!
b1010101 )!
b1010110 H!
0=
1<
#900000
0'
0-!
#905000
1'
1-!
b1010110 )!
b1010111 H!
1=
#910000
0'
0-!
#915000
1'
1-!
b1010111 )!
b1011000 H!
0=
0<
0;
1:
#920000
0'
0-!
#925000
1'
1-!
b1011000 )!
b1011001 H!
1=
#930000
0'
0-!
#935000
1'
1-!
b1011001 )!
b1011010 H!
0=
1<
#940000
0'
0-!
#945000
1'
1-!
b1011010 )!
b1011011 H!
1=
#950000
0'
0-!
#955000
1'
1-!
b1011011 )!
b1011100 H!
0=
0<
1;
#960000
0'
0-!
#965000
1'
1-!
b1011100 )!
b1011101 H!
1=
#970000
0'
0-!
#975000
1'
1-!
b1011101 )!
b1011110 H!
0=
1<
#980000
0'
0-!
#985000
1'
1-!
b1011110 )!
b1011111 H!
1=
#990000
0'
0-!
#995000
1'
1-!
b1011111 )!
b1100000 H!
0=
0<
0;
0:
09
18
#1000000
0'
0-!
#1005000
1'
1-!
b1100000 )!
b1100001 H!
1=
#1010000
0'
0-!
#1015000
1'
1-!
b1100001 )!
b1100010 H!
0=
1<
#1020000
0'
0-!
#1025000
1'
1-!
b1100010 )!
b1100011 H!
1=
#1030000
0'
0-!
#1035000
1'
1-!
b1100011 )!
b1100100 H!
0=
0<
1;
#1040000
0'
0-!
#1045000
1'
1-!
b1100100 )!
b1100101 H!
1=
#1050000
0'
0-!
#1055000
1'
1-!
b1100101 )!
b1100110 H!
0=
1<
#1060000
0'
0-!
#1065000
1'
1-!
b1100110 )!
b1100111 H!
1=
#1070000
0'
0-!
#1075000
1'
1-!
b1100111 )!
b1101000 H!
0=
0<
0;
1:
#1080000
0'
0-!
#1085000
1'
1-!
b1101000 )!
b1101001 H!
1=
#1090000
0'
0-!
#1095000
1'
1-!
b1101001 )!
b1101010 H!
0=
1<
#1100000
0'
0-!
#1105000
1'
1-!
b1101010 )!
b1101011 H!
1=
#1110000
0'
0-!
#1115000
1'
1-!
b1101011 )!
b1101100 H!
0=
0<
1;
#1120000
0'
0-!
#1125000
1'
1-!
b1101100 )!
b1101101 H!
1=
#1130000
0'
0-!
#1135000
1'
1-!
b1101101 )!
b1101110 H!
0=
1<
#1140000
0'
0-!
#1145000
1'
1-!
b1101110 )!
b1101111 H!
1=
#1150000
0'
0-!
#1155000
1'
1-!
b1101111 )!
b1110000 H!
0=
0<
0;
0:
19
#1160000
0'
0-!
#1165000
1'
1-!
b1110000 )!
b1110001 H!
1=
#1170000
0'
0-!
#1175000
1'
1-!
b1110001 )!
b1110010 H!
0=
1<
#1180000
0'
0-!
#1185000
1'
1-!
b1110010 )!
b1110011 H!
1=
#1190000
0'
0-!
#1195000
1'
1-!
b1110011 )!
b1110100 H!
0=
0<
1;
#1200000
0'
0-!
#1205000
1'
1-!
b1110100 )!
b1110101 H!
1=
#1210000
0'
0-!
#1215000
1'
1-!
b1110101 )!
b1110110 H!
0=
1<
#1220000
0'
0-!
#1225000
1'
1-!
b1110110 )!
b1110111 H!
1=
#1230000
0'
0-!
#1235000
1'
1-!
b1110111 )!
b1111000 H!
0=
0<
0;
1:
#1240000
0'
0-!
#1245000
1'
1-!
b1111000 )!
b1111001 H!
1=
#1250000
0'
0-!
#1255000
1'
1-!
b1111001 )!
b1111010 H!
0=
1<
#1260000
0'
0-!
#1265000
1'
1-!
b1111010 )!
b1111011 H!
1=
#1270000
0'
0-!
#1275000
1'
1-!
b1111011 )!
b1111100 H!
0=
0<
1;
#1280000
0'
0-!
#1285000
1'
1-!
b1111100 )!
b1111101 H!
1=
#1290000
0'
0-!
#1295000
1'
1-!
b1111101 )!
b1111110 H!
0=
1<
#1300000
0'
0-!
#1305000
1'
1-!
b1111110 )!
b1111111 H!
1=
#1310000
0'
0-!
#1315000
1'
1-!
b1111111 )!
b10000000 H!
0=
0<
0;
0:
09
08
07
16
#1320000
0'
0-!
#1325000
1'
1-!
b10000000 )!
b10000001 H!
1=
#1330000
0'
0-!
#1335000
1'
1-!
b10000001 )!
b10000010 H!
0=
1<
#1340000
0'
0-!
#1345000
1'
1-!
b10000010 )!
b10000011 H!
1=
#1350000
0'
0-!
#1355000
1'
1-!
b10000011 )!
b10000100 H!
0=
0<
1;
#1360000
0'
0-!
#1365000
1'
1-!
b10000100 )!
b10000101 H!
1=
#1370000
0'
0-!
#1375000
1'
1-!
b10000101 )!
b10000110 H!
0=
1<
#1380000
0'
0-!
#1385000
1'
1-!
b10000110 )!
b10000111 H!
1=
#1390000
0'
0-!
#1395000
1'
1-!
b10000111 )!
b10001000 H!
0=
0<
0;
1:
#1400000
0'
0-!
#1405000
1'
1-!
b10001000 )!
b10001001 H!
1=
#1410000
0'
0-!
#1415000
1'
1-!
b10001001 )!
b10001010 H!
0=
1<
#1420000
0'
0-!
#1425000
1'
1-!
b10001010 )!
b10001011 H!
1=
#1430000
0'
0-!
#1435000
1'
1-!
b10001011 )!
b10001100 H!
0=
0<
1;
#1440000
0'
0-!
#1445000
1'
1-!
b10001100 )!
b10001101 H!
1=
#1450000
0'
0-!
#1455000
1'
1-!
b10001101 )!
b10001110 H!
0=
1<
#1460000
0'
0-!
#1465000
1'
1-!
b10001110 )!
b10001111 H!
1=
#1470000
0'
0-!
#1475000
1'
1-!
b10001111 )!
b10010000 H!
0=
0<
0;
0:
19
#1480000
0'
0-!
#1485000
1'
1-!
b10010000 )!
b10010001 H!
1=
#1490000
0'
0-!
#1495000
1'
1-!
b10010001 )!
b10010010 H!
0=
1<
#1500000
0'
0-!
#1505000
1'
1-!
b10010010 )!
b10010011 H!
1=
#1510000
0'
0-!
#1515000
1'
1-!
b10010011 )!
b10010100 H!
0=
0<
1;
#1520000
0'
0-!
#1525000
1'
1-!
b10010100 )!
b10010101 H!
1=
#1530000
0'
0-!
#1535000
1'
1-!
b10010101 )!
b10010110 H!
0=
1<
#1540000
0'
0-!
#1545000
1'
1-!
b10010110 )!
b10010111 H!
1=
#1550000
0'
0-!
#1555000
1'
1-!
b10010111 )!
b10011000 H!
0=
0<
0;
1:
#1560000
0'
0-!
#1565000
1'
1-!
b10011000 )!
b10011001 H!
1=
#1570000
0'
0-!
#1575000
1'
1-!
b10011001 )!
b10011010 H!
0=
1<
#1580000
0'
0-!
#1585000
1'
1-!
b10011010 )!
b10011011 H!
1=
#1590000
0'
0-!
#1595000
1'
1-!
b10011011 )!
b10011100 H!
0=
0<
1;
#1600000
0'
0-!
#1605000
1'
1-!
b10011100 )!
b10011101 H!
1=
#1610000
0'
0-!
#1615000
1'
1-!
b10011101 )!
b10011110 H!
0=
1<
#1620000
0'
0-!
#1625000
1'
1-!
b10011110 )!
b10011111 H!
1=
#1630000
0'
0-!
#1635000
1'
1-!
b10011111 )!
b10100000 H!
0=
0<
0;
0:
09
18
#1640000
0'
0-!
#1645000
1'
1-!
b10100000 )!
b10100001 H!
1=
#1650000
0'
0-!
#1655000
1'
1-!
b10100001 )!
b10100010 H!
0=
1<
#1660000
0'
0-!
#1665000
1'
1-!
b10100010 )!
b10100011 H!
1=
#1670000
0'
0-!
#1675000
1'
1-!
b10100011 )!
b10100100 H!
0=
0<
1;
#1680000
0'
0-!
#1685000
1'
1-!
b10100100 )!
b10100101 H!
1=
#1690000
0'
0-!
#1695000
1'
1-!
b10100101 )!
b10100110 H!
0=
1<
#1700000
0'
0-!
#1705000
1'
1-!
b10100110 )!
b10100111 H!
1=
#1710000
0'
0-!
#1715000
1'
1-!
b10100111 )!
b10101000 H!
0=
0<
0;
1:
#1720000
0'
0-!
#1725000
1'
1-!
b10101000 )!
b10101001 H!
1=
#1730000
0'
0-!
#1735000
1'
1-!
b10101001 )!
b10101010 H!
0=
1<
#1740000
0'
0-!
