dev/Integration_TB/master/hamming_enc.v
// hamming_enc: Systematic Hamming [42,35] encoder with overall parity (SECDED)
// codeword[41:0] = { data[34:0], p[5:0], p_overall }
//   codeword[41:7] = data[34:0]
//   codeword[6:1]  = { p[5], p[4], p[3], p[2], p[1], p[0] }
//   codeword[0]    = p_overall  (XOR of all 41 bits above)
//
// Parity coverage (position = d-index + 1):
//   p[0]: positions where bit0=1  -> d[0,2,4,6,8,10,12,14,16,18,20,22,24,26,28,30,32,34]
//   p[1]: positions where bit1=1  -> d[1,2,5,6,9,10,13,14,17,18,21,22,25,26,29,30,33,34]
//   p[2]: positions where bit2=1  -> d[3,4,5,6,11,12,13,14,19,20,21,22,27,28,29,30]
//   p[3]: positions where bit3=1  -> d[7,8,9,10,11,12,13,14,23,24,25,26,27,28,29,30]
//   p[4]: positions where bit4=1  -> d[15..30]
//   p[5]: positions where bit5=1  -> d[31,32,33,34]
module hamming_enc (
    input  wire [34:0] data,
    output wire [41:0] codeword
);

    wire p0 = data[0] ^data[2] ^data[4] ^data[6] ^data[8] ^data[10]^data[12]^data[14]
             ^data[16]^data[18]^data[20]^data[22]^data[24]^data[26]^data[28]^data[30]
             ^data[32]^data[34];

    wire p1 = data[1] ^data[2] ^data[5] ^data[6] ^data[9] ^data[10]^data[13]^data[14]
             ^data[17]^data[18]^data[21]^data[22]^data[25]^data[26]^data[29]^data[30]
             ^data[33]^data[34];

    wire p2 = data[3] ^data[4] ^data[5] ^data[6] ^data[11]^data[12]^data[13]^data[14]
             ^data[19]^data[20]^data[21]^data[22]^data[27]^data[28]^data[29]^data[30];

    wire p3 = data[7] ^data[8] ^data[9] ^data[10]^data[11]^data[12]^data[13]^data[14]
             ^data[23]^data[24]^data[25]^data[26]^data[27]^data[28]^data[29]^data[30];

    wire p4 = data[15]^data[16]^data[17]^data[18]^data[19]^data[20]^data[21]^data[22]
             ^data[23]^data[24]^data[25]^data[26]^data[27]^data[28]^data[29]^data[30];

    wire p5 = data[31]^data[32]^data[33]^data[34];

    wire p_overall = ^{data, p5, p4, p3, p2, p1, p0};

    assign codeword = {data, p5, p4, p3, p2, p1, p0, p_overall};

endmodule

dev/Master/Master_tx.v
// master_tx: NRZ transmitter for TDMA master broadcast
// Bit period = div clk cycles (same as slave_tx)
// Frame: [preamble 8b = 0xAA][codeword 42b] = 50 bits
//   codeword = {halt_cmd[7:0], 27'b0, p[5:0], p_overall}  (systematic SECDED)
// GPIO_out is driven high/low while active; released (high-Z) when idle.
module Master_tx (
    input  wire        clk,
    input  wire        resetn,
    input  wire        tx_trigger,
    input  wire [7:0]  halt_cmd,
    input  wire [9:0]  GUARD_TICKS,
    input  wire [9:0]  DIV,

    output wire        GPIO_out
);

    reg [49:0] frame;
    reg [5:0]  bit_cnt;
    reg [9:0] tx_cnt;
    reg        tx_bit;
    reg       tx_active;


    // ----------------------------------------------------------------
    // Hamming systematic SECDED encoding via hamming_enc module
    // d[34:0] = {halt_cmd, GUARD_TICKS, DIV, 17'b0};
    // codeword[41:0] = {d[34:0], p[5:0], p_overall}
    // ----------------------------------------------------------------
    wire [34:0] d = {halt_cmd, GUARD_TICKS, 17'b0};

    wire [41:0] codeword;
    hamming_enc u_enc (.data(d), .codeword(codeword));

    // ----------------------------------------------------------------
    // tx counter and frame shift register
    // ----------------------------------------------------------------
    always @(posedge clk or negedge resetn) begin
        if (!resetn) begin
            tx_cnt   <= 11'd0;
            bit_cnt  <= 6'd0;
            tx_active<= 1'b0;
            frame    <= 50'd0;
            tx_bit   <= 1'b0;
        end else begin
            if (!tx_active) begin
                tx_cnt  <= 11'd0;
                bit_cnt <= 6'd0;
                if (tx_trigger) begin
                    frame     <= {8'hAA, codeword};
                    tx_active <= 1'b1;
                    tx_bit    <= 1'b1; // preamble MSB of 0xAA = 1
                end
            end else begin
                if (tx_cnt == DIV-1) begin
                    tx_cnt <= 11'd0;
                    if (bit_cnt == 6'd49) begin
                        tx_active <= 1'b0;
                        tx_bit    <= 1'b0;
                    end else begin
                        bit_cnt <= bit_cnt + 6'd1;
                        tx_bit  <= frame[49 - (bit_cnt + 6'd1)];
                    end
                end else begin
                    tx_cnt <= tx_cnt + 11'd1;
                end
            end
        end
    end

    assign GPIO_out = (tx_active) ? tx_bit : 1'b0;

endmodule

dev/Integration_TB/master/tb_master_tx.v
`timescale 1ns/1ps
// tb_master_tx: Master_tx 단위 테스트
// 컴파일: vlog hamming_enc.v Master_tx.v tb_master_tx.v
// 실행: vsim -c tb_master_tx -do "run -all; quit"
//
// 검증: data_trigger 후 50비트 NRZ 프레임 전송 확인 (preamble=0xAA)
//       sync_trigger 후 동일 프레임 재전송 확인 (겹치지 않음)
module tb_master_tx;

localparam CLK_HALF    = 5;
localparam [9:0] DIV   = 10'd4;
localparam [9:0] GUARD = 10'd20;
localparam [7:0] HALT  = 8'hAB;

reg clk = 0, resetn = 0;
always #CLK_HALF clk = ~clk;

reg tx_trigger;
wire GPIO_out;

Master_tx dut (
    .clk(clk), .resetn(resetn),
    .tx_trigger(tx_trigger), .halt_cmd(HALT),
    .GUARD_TICKS(GUARD), .DIV(DIV),
    .GPIO_out(GPIO_out)
);

integer fail = 0, pass = 0;
task chk;
    input cond;
    input [255:0] msg;
    begin
        if (cond) begin $display("  PASS | %0s", msg); pass = pass + 1; end
        else      begin $display("  FAIL | %0s", msg); fail = fail + 1; end
    end
endtask

// GPIO_out 비트 샘플링: 각 비트를 DIV 클럭 중간(DIV/2)에 샘플
task sample_frame;
    output [49:0] frame_out;
    integer b, d;
    reg bit_val;
    begin
        for (b = 0; b < 50; b = b + 1) begin
            // 비트 중간 지점까지 대기 (DIV/2 클럭)
            for (d = 0; d < DIV/2; d = d + 1)
                @(posedge clk);
            bit_val = GPIO_out;
            frame_out[49-b] = bit_val;
            // 나머지 반 주기
            for (d = DIV/2; d < DIV; d = d + 1)
                @(posedge clk);
        end
    end
endtask

reg [49:0] captured;

initial begin
    $dumpfile("tb_master_tx.vcd");
    $dumpvars(0, tb_master_tx);

    tx_trigger = 0;
    resetn = 0;
    repeat(4) @(posedge clk);
    resetn = 1;
    repeat(2) @(posedge clk);

    // --- SC1: data_trigger (마스터 DATA 슬롯 시뮬) ---
    $display("[%0t] SC1: data_trigger → 프레임 전송 검증", $time);
    @(posedge clk);
    tx_trigger = 1;
    @(posedge clk);
    tx_trigger = 0;

    // 프레임 샘플링: 50비트 × DIV클럭
    sample_frame(captured);
    @(posedge clk); // NB assignment 반영 대기

    chk(captured[49:42] == 8'hAA, "preamble == 0xAA");
    chk(GPIO_out == 1'b0,         "GPIO_out=0 after TX done");

    // --- SC2: sync_trigger (주기 끝 SYNC 시뮬) ---
    $display("[%0t] SC2: sync_trigger → 프레임 재전송 검증", $time);
    repeat(5) @(posedge clk);  // 약간의 idle 갭
    @(posedge clk);
    tx_trigger = 1;
    @(posedge clk);
    tx_trigger = 0;

    sample_frame(captured);
    @(posedge clk);

    chk(captured[49:42] == 8'hAA, "preamble == 0xAA (sync)");
    chk(GPIO_out == 1'b0,         "GPIO_out=0 after sync TX done");

    // --- SC3: tx_enable 없을 때 (resetn=0 후 재확인) ---
    $display("[%0t] SC3: 리셋 후 idle 상태 확인", $time);
    resetn = 0;
    @(posedge clk);
    resetn = 1;
    repeat(2) @(posedge clk);
    chk(GPIO_out == 1'b0, "GPIO_out=0 after reset, no trigger");

    $display("");
    $display("=== Result: %0d PASS  %0d FAIL ===", pass, fail);
    $finish;
end

initial begin #200_000; $display("TIMEOUT"); $finish; end

endmodule

dev/Integration_TB/tb_master_tx.vcd
$date
	Tue Jun 02 18:21:44 2026
$end
$version
	ModelSim Version 10.5b
$end
$timescale
	1ps
$end

$scope module tb_master_tx $end
$var parameter 32 ! CLK_HALF $end
$var parameter 10 " DIV $end
$var parameter 10 # GUARD $end
$var parameter 8 $ HALT $end
$var reg 1 % clk $end
$var reg 1 & resetn $end
$var reg 1 ' tx_trigger $end
$var wire 1 ( GPIO_out $end
$var integer 32 ) fail $end
$var integer 32 * pass $end
$var reg 50 + captured [49:0] $end

$scope task chk $end
$var reg 1 , cond $end
$var reg 256 - msg [255:0] $end
$upscope $end

$scope task sample_frame $end
$var reg 50 . frame_out [49:0] $end
$var integer 32 / b $end
$var integer 32 0 d $end
$var reg 1 1 bit_val $end
$upscope $end

$scope module dut $end
$var wire 1 2 clk $end
$var wire 1 3 resetn $end
$var wire 1 4 tx_trigger $end
$var wire 1 5 halt_cmd [7] $end
$var wire 1 6 halt_cmd [6] $end
$var wire 1 7 halt_cmd [5] $end
$var wire 1 8 halt_cmd [4] $end
$var wire 1 9 halt_cmd [3] $end
$var wire 1 : halt_cmd [2] $end
$var wire 1 ; halt_cmd [1] $end
$var wire 1 < halt_cmd [0] $end
$var wire 1 = GUARD_TICKS [9] $end
$var wire 1 > GUARD_TICKS [8] $end
$var wire 1 ? GUARD_TICKS [7] $end
$var wire 1 @ GUARD_TICKS [6] $end
$var wire 1 A GUARD_TICKS [5] $end
$var wire 1 B GUARD_TICKS [4] $end
$var wire 1 C GUARD_TICKS [3] $end
$var wire 1 D GUARD_TICKS [2] $end
$var wire 1 E GUARD_TICKS [1] $end
$var wire 1 F GUARD_TICKS [0] $end
$var wire 1 G DIV [9] $end
$var wire 1 H DIV [8] $end
$var wire 1 I DIV [7] $end
$var wire 1 J DIV [6] $end
$var wire 1 K DIV [5] $end
$var wire 1 L DIV [4] $end
$var wire 1 M DIV [3] $end
$var wire 1 N DIV [2] $end
$var wire 1 O DIV [1] $end
$var wire 1 P DIV [0] $end
$var wire 1 ( GPIO_out $end
$var reg 50 Q frame [49:0] $end
$var reg 6 R bit_cnt [5:0] $end
$var reg 10 S tx_cnt [9:0] $end
$var reg 1 T tx_bit $end
$var reg 1 U tx_active $end
$var wire 1 V d [34] $end
$var wire 1 W d [33] $end
$var wire 1 X d [32] $end
$var wire 1 Y d [31] $end
$var wire 1 Z d [30] $end
$var wire 1 [ d [29] $end
$var wire 1 \ d [28] $end
$var wire 1 ] d [27] $end
$var wire 1 ^ d [26] $end
$var wire 1 _ d [25] $end
$var wire 1 ` d [24] $end
$var wire 1 a d [23] $end
$var wire 1 b d [22] $end
$var wire 1 c d [21] $end
$var wire 1 d d [20] $end
$var wire 1 e d [19] $end
$var wire 1 f d [18] $end
$var wire 1 g d [17] $end
$var wire 1 h d [16] $end
$var wire 1 i d [15] $end
$var wire 1 j d [14] $end
$var wire 1 k d [13] $end
$var wire 1 l d [12] $end
$var wire 1 m d [11] $end
$var wire 1 n d [10] $end
$var wire 1 o d [9] $end
$var wire 1 p d [8] $end
$var wire 1 q d [7] $end
$var wire 1 r d [6] $end
$var wire 1 s d [5] $end
$var wire 1 t d [4] $end
$var wire 1 u d [3] $end
$var wire 1 v d [2] $end
$var wire 1 w d [1] $end
$var wire 1 x d [0] $end
$var wire 1 y codeword [41] $end
$var wire 1 z codeword [40] $end
$var wire 1 { codeword [39] $end
$var wire 1 | codeword [38] $end
$var wire 1 } codeword [37] $end
$var wire 1 ~ codeword [36] $end
$var wire 1 !! codeword [35] $end
$var wire 1 "! codeword [34] $end
$var wire 1 #! codeword [33] $end
$var wire 1 $! codeword [32] $end
$var wire 1 %! codeword [31] $end
$var wire 1 &! codeword [30] $end
$var wire 1 '! codeword [29] $end
$var wire 1 (! codeword [28] $end
$var wire 1 )! codeword [27] $end
$var wire 1 *! codeword [26] $end
$var wire 1 +! codeword [25] $end
$var wire 1 ,! codeword [24] $end
$var wire 1 -! codeword [23] $end
$var wire 1 .! codeword [22] $end
$var wire 1 /! codeword [21] $end
$var wire 1 0! codeword [20] $end
$var wire 1 1! codeword [19] $end
$var wire 1 2! codeword [18] $end
$var wire 1 3! codeword [17] $end
$var wire 1 4! codeword [16] $end
$var wire 1 5! codeword [15] $end
$var wire 1 6! codeword [14] $end
$var wire 1 7! codeword [13] $end
$var wire 1 8! codeword [12] $end
$var wire 1 9! codeword [11] $end
$var wire 1 :! codeword [10] $end
$var wire 1 ;! codeword [9] $end
$var wire 1 <! codeword [8] $end
$var wire 1 =! codeword [7] $end
$var wire 1 >! codeword [6] $end
$var wire 1 ?! codeword [5] $end
$var wire 1 @! codeword [4] $end
$var wire 1 A! codeword [3] $end
$var wire 1 B! codeword [2] $end
$var wire 1 C! codeword [1] $end
$var wire 1 D! codeword [0] $end

$scope module u_enc $end
$var wire 1 V data [34] $end
$var wire 1 W data [33] $end
$var wire 1 X data [32] $end
$var wire 1 Y data [31] $end
$var wire 1 Z data [30] $end
$var wire 1 [ data [29] $end
$var wire 1 \ data [28] $end
$var wire 1 ] data [27] $end
$var wire 1 ^ data [26] $end
$var wire 1 _ data [25] $end
$var wire 1 ` data [24] $end
$var wire 1 a data [23] $end
$var wire 1 b data [22] $end
$var wire 1 c data [21] $end
$var wire 1 d data [20] $end
$var wire 1 e data [19] $end
$var wire 1 f data [18] $end
$var wire 1 g data [17] $end
$var wire 1 h data [16] $end
$var wire 1 i data [15] $end
$var wire 1 j data [14] $end
$var wire 1 k data [13] $end
$var wire 1 l data [12] $end
$var wire 1 m data [11] $end
$var wire 1 n data [10] $end
$var wire 1 o data [9] $end
$var wire 1 p data [8] $end
$var wire 1 q data [7] $end
$var wire 1 r data [6] $end
$var wire 1 s data [5] $end
$var wire 1 t data [4] $end
$var wire 1 u data [3] $end
$var wire 1 v data [2] $end
$var wire 1 w data [1] $end
$var wire 1 x data [0] $end
$var wire 1 y codeword [41] $end
$var wire 1 z codeword [40] $end
$var wire 1 { codeword [39] $end
$var wire 1 | codeword [38] $end
$var wire 1 } codeword [37] $end
$var wire 1 ~ codeword [36] $end
$var wire 1 !! codeword [35] $end
$var wire 1 "! codeword [34] $end
$var wire 1 #! codeword [33] $end
$var wire 1 $! codeword [32] $end
$var wire 1 %! codeword [31] $end
$var wire 1 &! codeword [30] $end
$var wire 1 '! codeword [29] $end
$var wire 1 (! codeword [28] $end
$var wire 1 )! codeword [27] $end
$var wire 1 *! codeword [26] $end
$var wire 1 +! codeword [25] $end
$var wire 1 ,! codeword [24] $end
$var wire 1 -! codeword [23] $end
$var wire 1 .! codeword [22] $end
$var wire 1 /! codeword [21] $end
$var wire 1 0! codeword [20] $end
$var wire 1 1! codeword [19] $end
$var wire 1 2! codeword [18] $end
$var wire 1 3! codeword [17] $end
$var wire 1 4! codeword [16] $end
$var wire 1 5! codeword [15] $end
$var wire 1 6! codeword [14] $end
$var wire 1 7! codeword [13] $end
$var wire 1 8! codeword [12] $end
$var wire 1 9! codeword [11] $end
$var wire 1 :! codeword [10] $end
$var wire 1 ;! codeword [9] $end
$var wire 1 <! codeword [8] $end
$var wire 1 =! codeword [7] $end
$var wire 1 >! codeword [6] $end
$var wire 1 ?! codeword [5] $end
$var wire 1 @! codeword [4] $end
$var wire 1 A! codeword [3] $end
$var wire 1 B! codeword [2] $end
$var wire 1 C! codeword [1] $end
$var wire 1 D! codeword [0] $end
$var wire 1 E! p0 $end
$var wire 1 F! p1 $end
$var wire 1 G! p2 $end
$var wire 1 H! p3 $end
$var wire 1 I! p4 $end
$var wire 1 J! p5 $end
$var wire 1 K! p_overall $end
$upscope $end
$upscope $end
$upscope $end
$enddefinitions $end
#0
$dumpvars
0%
0&
0'
b0 Q
b0 R
b0 S
0T
0U
x,
bx -
bx .
x1
bx +
b101 !
b100 "
b10100 #
b10101011 $
b0 )
b0 *
bx /
bx 0
0(
0x
0w
0v
0u
0t
0s
0r
0q
0p
0o
0n
0m
0l
0k
0j
0i
0h
0g
0f
1e
0d
1c
0b
0a
0`
0_
0^
1]
1\
0[
1Z
0Y
1X
0W
1V
1D!
0C!
1B!
1A!
1@!
1?!
0>!
0=!
0<!
0;!
0:!
09!
08!
07!
06!
05!
04!
03!
02!
01!
00!
0/!
0.!
0-!
0,!
0+!
1*!
0)!
1(!
0'!
0&!
0%!
0$!
0#!
1"!
1!!
0~
1}
0|
1{
0z
1y
0E!
1F!
1G!
1H!
1I!
0J!
1K!
0P
0O
1N
0M
0L
0K
0J
0I
0H
0G
0F
0E
1D
0C
1B
0A
0@
0?
0>
0=
1<
1;
0:
19
08
17
06
15
04
03
02
$end
#5000
1%
12
#10000
0%
02
#15000
1%
12
#20000
0%
02
#25000
1%
12
#30000
0%
02
#35000
1%
12
1&
13
#40000
0%
02
#45000
1%
12
#50000
0%
02
#55000
1%
12
#60000
0%
02
#65000
1%
12
1'
14
#70000
0%
02
#75000
1%
12
0'
b0 /
b0 0
04
b10101010101010110000010100000000000000000000111101 Q
1U
1T
1(
#80000
0%
02
#85000
1%
12
b1 0
b1 S
#90000
0%
02
#95000
1%
12
b10 0
11
b1xxxxxxxxxxxxxxxxxxxxxxxxxxxxxxxxxxxxxxxxxxxxxxxxx .
b10 S
#100000
0%
02
#105000
1%
12
b11 0
b11 S
#110000
0%
02
#115000
1%
12
b100 0
b1 /
b0 0
b0 S
b1 R
0T
0(
#120000
0%
02
#125000
1%
12
b1 0
b1 S
#130000
0%
02
#135000
1%
12
b10 0
01
b10xxxxxxxxxxxxxxxxxxxxxxxxxxxxxxxxxxxxxxxxxxxxxxxx .
b10 S
#140000
0%
02
#145000
1%
12
b11 0
b11 S
#150000
0%
02
#155000
1%
12
b100 0
b10 /
b0 0
b0 S
b10 R
1T
1(
#160000
0%
02
#165000
1%
12
b1 0
b1 S
#170000
0%
02
#175000
1%
12
b10 0
11
b101xxxxxxxxxxxxxxxxxxxxxxxxxxxxxxxxxxxxxxxxxxxxxxx .
b10 S
#180000
0%
02
#185000
1%
12
b11 0
b11 S
#190000
0%
02
#195000
1%
12
b100 0
b11 /
b0 0
b0 S
b11 R
0T
0(
#200000
0%
02
#205000
1%
12
b1 0
b1 S
#210000
0%
02
#215000
1%
12
b10 0
01
b1010xxxxxxxxxxxxxxxxxxxxxxxxxxxxxxxxxxxxxxxxxxxxxx .
b10 S
#220000
0%
02
#225000
1%
12
b11 0
b11 S
#230000
0%
02
#235000
1%
12
b100 0
b100 /
b0 0
b0 S
b100 R
1T
1(
#240000
0%
02
#245000
1%
12
b1 0
b1 S
#250000
0%
02
#255000
1%
12
b10 0
11
b10101xxxxxxxxxxxxxxxxxxxxxxxxxxxxxxxxxxxxxxxxxxxxx .
b10 S
#260000
0%
02
#265000
1%
12
b11 0
b11 S
#270000
0%
02
#275000
1%
12
b100 0
b101 /
b0 0
b0 S
b101 R
0T
0(
#280000
0%
02
#285000
1%
12
b1 0
b1 S
#290000
0%
02
#295000
1%
12
b10 0
01
b101010xxxxxxxxxxxxxxxxxxxxxxxxxxxxxxxxxxxxxxxxxxxx .
b10 S
#300000
0%
02
#305000
1%
12
b11 0
b11 S
#310000
0%
02
#315000
1%
12
b100 0
b110 /
b0 0
b0 S
b110 R
1T
1(
#320000
0%
02
#325000
1%
12
b1 0
b1 S
#330000
0%
02
#335000
1%
12
b10 0
11
b1010101xxxxxxxxxxxxxxxxxxxxxxxxxxxxxxxxxxxxxxxxxxx .
b10 S
#340000
0%
02
#345000
1%
12
b11 0
b11 S
#350000
0%
02
#355000
1%
12
b100 0
b111 /
b0 0
b0 S
b111 R
0T
0(
#360000
0%
02
#365000
1%
12
b1 0
b1 S
#370000
0%
02
#375000
1%
12
b10 0
01
b10101010xxxxxxxxxxxxxxxxxxxxxxxxxxxxxxxxxxxxxxxxxx .
b10 S
#380000
0%
02
#385000
1%
12
b11 0
b11 S
#390000
0%
02
#395000
1%
12
b100 0
b1000 /
b0 0
b0 S
b1000 R
1T
1(
#400000
0%
02
#405000
1%
12
b1 0
b1 S
#410000
0%
02
#415000
1%
12
b10 0
11
b101010101xxxxxxxxxxxxxxxxxxxxxxxxxxxxxxxxxxxxxxxxx .
b10 S
#420000
0%
02
#425000
1%
12
b11 0
b11 S
#430000
0%
02
#435000
1%
12
b100 0
b1001 /
b0 0
b0 S
b1001 R
0T
0(
#440000
0%
02
#445000
1%
12
b1 0
b1 S
#450000
0%
02
#455000
1%
12
b10 0
01
b1010101010xxxxxxxxxxxxxxxxxxxxxxxxxxxxxxxxxxxxxxxx .
b10 S
#460000
0%
02
#465000
1%
12
b11 0
b11 S
#470000
0%
02
#475000
1%
12
b100 0
b1010 /
b0 0
b0 S
b1010 R
1T
1(
#480000
0%
02
#485000
1%
12
b1 0
b1 S
#490000
0%
02
#495000
1%
12
b10 0
11
b10101010101xxxxxxxxxxxxxxxxxxxxxxxxxxxxxxxxxxxxxxx .
b10 S
#500000
0%
02
#505000
1%
12
b11 0
b11 S
#510000
0%
02
#515000
1%
12
b100 0
b1011 /
b0 0
b0 S
b1011 R
0T
0(
#520000
0%
02
#525000
1%
12
b1 0
b1 S
#530000
0%
02
#535000
1%
12
b10 0
01
b101010101010xxxxxxxxxxxxxxxxxxxxxxxxxxxxxxxxxxxxxx .
b10 S
#540000
0%
02
#545000
1%
12
b11 0
b11 S
#550000
0%
02
#555000
1%
12
b100 0
b1100 /
b0 0
b0 S
b1100 R
1T
1(
#560000
0%
02
#565000
1%
12
b1 0
b1 S
#570000
0%
02
#575000
1%
12
b10 0
11
b1010101010101xxxxxxxxxxxxxxxxxxxxxxxxxxxxxxxxxxxxx .
b10 S
#580000
0%
02
#585000
1%
12
b11 0
b11 S
#590000
0%
02
#595000
1%
12
b100 0
b1101 /
b0 0
b0 S
b1101 R
0T
0(
#600000
0%
02
#605000
1%
12
b1 0
b1 S
#610000
0%
02
#615000
1%
12
b10 0
01
b10101010101010xxxxxxxxxxxxxxxxxxxxxxxxxxxxxxxxxxxx .
b10 S
#620000
0%
02
#625000
1%
12
b11 0
b11 S
#630000
0%
02
#635000
1%
12
b100 0
b1110 /
b0 0
b0 S
b1110 R
1T
1(
#640000
0%
02
#645000
1%
12
b1 0
b1 S
#650000
0%
02
#655000
1%
12
b10 0
11
b101010101010101xxxxxxxxxxxxxxxxxxxxxxxxxxxxxxxxxxx .
b10 S
#660000
0%
02
#665000
1%
12
b11 0
b11 S
#670000
0%
02
#675000
1%
12
b100 0
b1111 /
b0 0
b0 S
b1111 R
#680000
0%
02
#685000
1%
12
b1 0
b1 S
#690000
0%
02
#695000
1%
12
b10 0
b1010101010101011xxxxxxxxxxxxxxxxxxxxxxxxxxxxxxxxxx .
b10 S
#700000
0%
02
#705000
1%
12
b11 0
b11 S
#710000
0%
02
#715000
1%
12
b100 0
b10000 /
b0 0
b0 S
b10000 R
0T
0(
#720000
0%
02
#725000
1%
12
b1 0
b1 S
#730000
0%
02
#735000
1%
12
b10 0
01
b10101010101010110xxxxxxxxxxxxxxxxxxxxxxxxxxxxxxxxx .
b10 S
#740000
0%
02
#745000
1%
12
b11 0
b11 S
#750000
0%
02
#755000
1%
12
b100 0
b10001 /
b0 0
b0 S
b10001 R
#760000
0%
02
#765000
1%
12
b1 0
b1 S
#770000
0%
02
#775000
1%
12
b10 0
b101010101010101100xxxxxxxxxxxxxxxxxxxxxxxxxxxxxxxx .
b10 S
#780000
0%
02
#785000
1%
12
b11 0
b11 S
#790000
0%
02
#795000
1%
12
b100 0
b10010 /
b0 0
b0 S
b10010 R
#800000
0%
02
#805000
1%
12
b1 0
b1 S
#810000
0%
02
#815000
1%
12
b10 0
b1010101010101011000xxxxxxxxxxxxxxxxxxxxxxxxxxxxxxx .
b10 S
#820000
0%
02
#825000
1%
12
b11 0
b11 S
#830000
0%
02
#835000
1%
12
b100 0
b10011 /
b0 0
b0 S
b10011 R
#840000
0%
02
#845000
1%
12
b1 0
b1 S
#850000
0%
02
#855000
1%
12
b10 0
b10101010101010110000xxxxxxxxxxxxxxxxxxxxxxxxxxxxxx .
b10 S
#860000
0%
02
#865000
1%
12
b11 0
b11 S
#870000
0%
02
#875000
1%
12
b100 0
b10100 /
b0 0
b0 S
b10100 R
#880000
0%
02
#885000
1%
12
b1 0
b1 S
#890000
0%
02
#895000
1%
12
b10 0
b101010101010101100000xxxxxxxxxxxxxxxxxxxxxxxxxxxxx .
b10 S
#900000
0%
02
#905000
1%
12
b11 0
b11 S
#910000
0%
02
#915000
1%
12
b100 0
b10101 /
b0 0
b0 S
b10101 R
1T
1(
#920000
0%
02
#925000
1%
12
b1 0
b1 S
#930000
0%
02
#935000
1%
12
b10 0
11
b1010101010101011000001xxxxxxxxxxxxxxxxxxxxxxxxxxxx .
b10 S
#940000
0%
02
#945000
1%
12
b11 0
b11 S
#950000
0%
02
#955000
1%
12
b100 0
b10110 /
b0 0
b0 S
b10110 R
0T
0(
#960000
0%
02
#965000
1%
12
b1 0
b1 S
#970000
0%
02
#975000
1%
12
b10 0
01
b10101010101010110000010xxxxxxxxxxxxxxxxxxxxxxxxxxx .
b10 S
#980000
0%
02
#985000
1%
12
b11 0
b11 S
#990000
0%
02
#995000
1%
12
b100 0
b10111 /
b0 0
b0 S
b10111 R
1T
1(
#1000000
0%
02
#1005000
1%
12
b1 0
b1 S
#1010000
0%
02
#1015000
1%
12
b10 0
11
b101010101010101100000101xxxxxxxxxxxxxxxxxxxxxxxxxx .
b10 S
#1020000
0%
02
#1025000
1%
12
b11 0
b11 S
#1030000
0%
02
#1035000
1%
12
b100 0
b11000 /
b0 0
b0 S
b11000 R
0T
0(
#1040000
0%
02
#1045000
1%
12
b1 0
b1 S
#1050000
0%
02
#1055000
1%
12
b10 0
01
b1010101010101011000001010xxxxxxxxxxxxxxxxxxxxxxxxx .
b10 S
#1060000
0%
02
#1065000
1%
12
b11 0
b11 S
#1070000
0%
02
#1075000
1%
12
b100 0
b11001 /
b0 0
b0 S
b11001 R
#1080000
0%
02
#1085000
1%
12
b1 0
b1 S
#1090000
0%
02
#1095000
1%
12
b10 0
b10101010101010110000010100xxxxxxxxxxxxxxxxxxxxxxxx .
b10 S
#1100000
0%
02
#1105000
1%
12
b11 0
b11 S
#1110000
0%
02
#1115000
1%
12
b100 0
b11010 /
b0 0
b0 S
b11010 R
#1120000
0%
02
#1125000
1%
12
b1 0
b1 S
#1130000
0%
02
#1135000
1%
12
b10 0
b101010101010101100000101000xxxxxxxxxxxxxxxxxxxxxxx .
b10 S
#1140000
0%
02
#1145000
1%
12
b11 0
b11 S
#1150000
0%
02
#1155000
1%
12
b100 0
b11011 /
b0 0
b0 S
b11011 R
#1160000
0%
02
#1165000
1%
12
b1 0
b1 S
#1170000
0%
02
#1175000
1%
12
b10 0
b1010101010101011000001010000xxxxxxxxxxxxxxxxxxxxxx .
b10 S
#1180000
0%
02
#1185000
1%
12
b11 0
b11 S
#1190000
0%
02
#1195000
1%
12
b100 0
b11100 /
b0 0
b0 S
b11100 R
#1200000
0%
02
#1205000
1%
12
b1 0
b1 S
#1210000
0%
02
#1215000
1%
12
b10 0
b10101010101010110000010100000xxxxxxxxxxxxxxxxxxxxx .
b10 S
#1220000
0%
02
#1225000
1%
12
b11 0
b11 S
#1230000
0%
02
#1235000
1%
12
b100 0
b11101 /
b0 0
b0 S
b11101 R
#1240000
0%
02
#1245000
1%
12
b1 0
b1 S
#1250000
0%
02
#1255000
1%
12
b10 0
b101010101010101100000101000000xxxxxxxxxxxxxxxxxxxx .
b10 S
#1260000
0%
02
#1265000
1%
12
b11 0
b11 S
#1270000
0%
02
#1275000
1%
12
b100 0
b11110 /
b0 0
b0 S
b11110 R
#1280000
0%
02
#1285000
1%
12
b1 0
b1 S
#1290000
0%
02
#1295000
1%
12
b10 0
b1010101010101011000001010000000xxxxxxxxxxxxxxxxxxx .
b10 S
#1300000
0%
02
#1305000
1%
12
b11 0
b11 S
#1310000
0%
02
#1315000
1%
12
b100 0
b11111 /
b0 0
b0 S
b11111 R
#1320000
0%
02
#1325000
1%
12
b1 0
b1 S
#1330000
0%
02
#1335000
1%
12
b10 0
b10101010101010110000010100000000xxxxxxxxxxxxxxxxxx .
b10 S
#1340000
0%
02
#1345000
1%
12
b11 0
b11 S
#1350000
0%
02
#1355000
1%
12
b100 0
b100000 /
b0 0
b0 S
b100000 R
#1360000
0%
02
#1365000
1%
12
b1 0
b1 S
#1370000
0%
02
#1375000
1%
12
b10 0
b101010101010101100000101000000000xxxxxxxxxxxxxxxxx .
b10 S
#1380000
0%
02
#1385000
1%
12
b11 0
b11 S
#1390000
0%
02
#1395000
1%
12
b100 0
b100001 /
b0 0
b0 S
b100001 R
#1400000
0%
02
#1405000
1%
12
b1 0
b1 S
#1410000
0%
02
#1415000
1%
12
b10 0
b1010101010101011000001010000000000xxxxxxxxxxxxxxxx .
b10 S
#1420000
0%
02
#1425000
1%
12
b11 0
b11 S
#1430000
0%
02
#1435000
1%
12
b100 0
b100010 /
b0 0
b0 S
b100010 R
#1440000
0%
02
#1445000
1%
12
b1 0
b1 S
#1450000
0%
02
#1455000
1%
12
b10 0
b10101010101010110000010100000000000xxxxxxxxxxxxxxx .
b10 S
#1460000
0%
02
#1465000
1%
12
b11 0
b11 S
#1470000
0%
02
#1475000
1%
12
b100 0
b100011 /
b0 0
b0 S
b100011 R
#1480000
0%
02
#1485000
1%
12
b1 0
b1 S
#1490000
0%
02
#1495000
1%
12
b10 0
b101010101010101100000101000000000000xxxxxxxxxxxxxx .
b10 S
#1500000
0%
02
#1505000
1%
12
b11 0
b11 S
#1510000
0%
02
#1515000
1%
12
b100 0
b100100 /
b0 0
b0 S
b100100 R
#1520000
0%
02
#1525000
1%
12
b1 0
b1 S
#1530000
0%
02
#1535000
1%
12
b10 0
b1010101010101011000001010000000000000xxxxxxxxxxxxx .
b10 S
#1540000
0%
02
#1545000
1%
12
b11 0
b11 S
#1550000
0%
02
#1555000
1%
12
b100 0
b100101 /
b0 0
b0 S
b100101 R
#1560000
0%
02
#1565000
1%
12
b1 0
b1 S
#1570000
0%
02
#1575000
1%
12
b10 0
b10101010101010110000010100000000000000xxxxxxxxxxxx .
b10 S
#1580000
0%
02
#1585000
1%
12
b11 0
b11 S
#1590000
0%
02
